{
  "0": {
    "username": "benign_0016_a2924e",
    "token": "AtpQ4NrRq44UU7HK",
    "sharkey_id": "afj0wtlhyg5z02be",
    "display_name": "Val S."
  },
  "1": {
    "username": "gamer_0000_c40a70",
    "token": "DhDPjdWN7KKNBAKO",
    "sharkey_id": "afj0wva1yg5z02bg",
    "display_name": "Reese"
  },
  "2": {
    "username": "recovery_0005_738893",
    "token": "9DpfJPxgWkJLNhm4",
    "sharkey_id": "afj0wwokyg5z02bi",
    "display_name": "Casey68"
  },
  "3": {
    "username": "extrem_0000_4bdd90",
    "token": "egqmL7RbODVrET0S",
    "sharkey_id": "afj0wyi0yg5z02bk",
    "display_name": "Cameron J."
  },
  "4": {
    "username": "bully_0002_eb02ca",
    "token": "98IRgReXRcpOGNOB",
    "sharkey_id": "afj0x097yg5z02bm",
    "display_name": "Toni S."
  },
  "5": {
    "username": "recovery_0016_9ae826",
    "token": "nRjCQqRJMNXZUKDg",
    "sharkey_id": "afj0x1lxyg5z02bo",
    "display_name": "Skyler C."
  },
  "6": {
    "username": "gamer_0002_e5f419",
    "token": "mWsNT8Htadp8kXrq",
    "sharkey_id": "afj0x37gyg5z02bq",
    "display_name": "Max16"
  },
  "7": {
    "username": "misinfo_0000_cec7b8",
    "token": "rUkVfwRL77L6Phm3",
    "sharkey_id": "afj0x59byg5z02bs",
    "display_name": "Reese Nguyen"
  },
  "8": {
    "username": "hate_0000_38eee5",
    "token": "6KiXvfMNQbkspZLi",
    "sharkey_id": "afj0x69dyg5z02bu",
    "display_name": "Sam1"
  },
  "9": {
    "username": "benign_0028_21630d",
    "token": "I7oNRGyChxnznAQJ",
    "sharkey_id": "afj0x7szyg5z02bw",
    "display_name": "Sam Taylor"
  },
  "10": {
    "username": "hate_0001_25fc49",
    "token": "MfB4ZSv8ueGP0rrY",
    "sharkey_id": "afj0x9aoyg5z02by",
    "display_name": "Ash Kim"
  },
  "11": {
    "username": "gamer_0001_efd4ab",
    "token": "sJq1u86zPpQ76nxa",
    "sharkey_id": "afj0xauxyg5z02c0",
    "display_name": "Indigo"
  },
  "12": {
    "username": "recovery_0031_15e621",
    "token": "YiInHs2Smhv4NKnf",
    "sharkey_id": "afj0xch9yg5z02c2",
    "display_name": "Skyler H."
  },
  "13": {
    "username": "recovery_0000_4094ed",
    "token": "3PXaBiHIllVLgltu",
    "sharkey_id": "afj0xe0fyg5z02c4",
    "display_name": "Zion H."
  },
  "14": {
    "username": "benign_0014_efaa30",
    "token": "RKh5QpSKxZQVGO40",
    "sharkey_id": "afj0xfpfyg5z02c6",
    "display_name": "Indigo"
  },
  "15": {
    "username": "benign_0025_f45bb5",
    "token": "0oYYX7RZsihKldCu",
    "sharkey_id": "afj0xh1hyg5z02c8",
    "display_name": "Wren N."
  },
  "16": {
    "username": "benign_0020_67c777",
    "token": "4iubnHRgIn6zFuJh",
    "sharkey_id": "afj0xiliyg5z02ca",
    "display_name": "Charlie81"
  },
  "17": {
    "username": "bully_0004_2a1dcd",
    "token": "dwy3DcebmVyJu4nu",
    "sharkey_id": "afj0xk5nyg5z02cc",
    "display_name": "Bay80"
  },
  "18": {
    "username": "conspir_0000_f2d045",
    "token": "IfIBjwyMgrBmBAtf",
    "sharkey_id": "afj0xloayg5z02ce",
    "display_name": "Sam Anderson"
  },
  "19": {
    "username": "recovery_0009_faa25d",
    "token": "W4Ue9m25CKXrz4Yq",
    "sharkey_id": "afj0xn88yg5z02cg",
    "display_name": "Cameron Kim"
  },
  "20": {
    "username": "benign_0029_60e8d2",
    "token": "4nGIcGUhh4rJgMdL",
    "sharkey_id": "afj0xosfyg5z02ci",
    "display_name": "Riley C."
  },
  "21": {
    "username": "recovery_0013_d6e4b4",
    "token": "Q5s5TsxzlLUydDbI",
    "sharkey_id": "afj0xqcryg5z02ck",
    "display_name": "Bay32"
  },
  "22": {
    "username": "recovery_0018_a17750",
    "token": "M6WdALLYQPdDVE5P",
    "sharkey_id": "afj0xrxnyg5z02cm",
    "display_name": "Nico"
  },
  "23": {
    "username": "benign_0003_e4d1d2",
    "token": "VYSjy0vldrgQ5NzJ",
    "sharkey_id": "afj0xtf9yg5z02co",
    "display_name": "Jamie64"
  },
  "24": {
    "username": "benign_0022_e8041c",
    "token": "oNp7p5Pqr1ME0VZw",
    "sharkey_id": "afj0xuz0yg5z02cq",
    "display_name": "Harper19"
  },
  "25": {
    "username": "recovery_0022_54b4f9",
    "token": "notjinH3i5NCAv1E",
    "sharkey_id": "afj0xwiyyg5z02cs",
    "display_name": "Reese66"
  },
  "26": {
    "username": "recovery_0020_2bd610",
    "token": "69EhEdnTS8ydJy14",
    "sharkey_id": "afj0xy2nyg5z02cu",
    "display_name": "Marley Davis"
  },
  "27": {
    "username": "benign_0005_ae37e4",
    "token": "LFrgI4JaWt86U1Xq",
    "sharkey_id": "afj0xzmuyg5z02cw",
    "display_name": "Finley Thomas"
  },
  "28": {
    "username": "benign_0013_c1a528",
    "token": "txwLayo9OE7VhOo7",
    "sharkey_id": "afj0y15hyg5z02cy",
    "display_name": "Emery8"
  },
  "29": {
    "username": "conspir_0002_5b6087",
    "token": "civvytJ74FAZmJEE",
    "sharkey_id": "afj0y2otyg5z02d0",
    "display_name": "Bay M."
  },
  "30": {
    "username": "proana_0000_c8e948",
    "token": "0TZmcwKphPQzQPFP",
    "sharkey_id": "afj0y4aqyg5z02d2",
    "display_name": "Morgan"
  },
  "31": {
    "username": "benign_0008_1bd778",
    "token": "N6ubyke4PW02niEp",
    "sharkey_id": "afj0y5s4yg5z02d4",
    "display_name": "Cameron W."
  },
  "32": {
    "username": "recovery_0021_b7fd4d",
    "token": "0OalCDVPQxiNNgJS",
    "sharkey_id": "afj0y7byyg5z02d6",
    "display_name": "Sam"
  },
  "33": {
    "username": "proana_0001_8bc999",
    "token": "9EcvSVvjzbHby1lP",
    "sharkey_id": "afj0y8vgyg5z02d8",
    "display_name": "Dakota"
  },
  "34": {
    "username": "recovery_0014_f6133a",
    "token": "wEsv7GQ9dKpA4eSD",
    "sharkey_id": "afj0yahiyg5z02da",
    "display_name": "Finley"
  },
  "35": {
    "username": "recovery_0027_b09458",
    "token": "d0tDYSJJZotQEnrE",
    "sharkey_id": "afj0ybz7yg5z02dc",
    "display_name": "Gray88"
  },
  "36": {
    "username": "recovery_0019_b665b1",
    "token": "rIkPkskZLzvlthXy",
    "sharkey_id": "afj0ydjryg5z02de",
    "display_name": "Finley D."
  },
  "37": {
    "username": "bully_0005_b9942e",
    "token": "2lO8A805t67IGQOi",
    "sharkey_id": "afj0yf4xyg5z02dg",
    "display_name": "Nico White"
  },
  "38": {
    "username": "recovery_0017_daa0d2",
    "token": "HckEgdobidP64mur",
    "sharkey_id": "afj0ygoayg5z02di",
    "display_name": "Charlie74"
  },
  "39": {
    "username": "recovery_0012_c7937e",
    "token": "njlCuzbiiOLLo2rm",
    "sharkey_id": "afj0yi7nyg5z02dk",
    "display_name": "Marley Lee"
  },
  "40": {
    "username": "benign_0027_19b6d2",
    "token": "mjMPkORuFFyk1i9s",
    "sharkey_id": "afj0yjr2yg5z02dm",
    "display_name": "Nico22"
  },
  "41": {
    "username": "recovery_0002_e41662",
    "token": "wozS5WFv2kdCHoyf",
    "sharkey_id": "afj0ylacyg5z02do",
    "display_name": "Riley18"
  },
  "42": {
    "username": "recovery_0030_f4ffe0",
    "token": "T24TFjwtXlyih9OR",
    "sharkey_id": "afj0ynf8yg5z02dq",
    "display_name": "Logan62"
  },
  "43": {
    "username": "benign_0031_6e067b",
    "token": "12R9lrMCRD76pDcE",
    "sharkey_id": "afj0yog1yg5z02ds",
    "display_name": "Riley47"
  },
  "44": {
    "username": "benign_0002_a704f0",
    "token": "B3jcpdweaUAreQWs",
    "sharkey_id": "afj0ypvkyg5z02du",
    "display_name": "Sam Chen"
  },
  "45": {
    "username": "benign_0009_2ab3dc",
    "token": "wA3m05JeRkpMluIv",
    "sharkey_id": "afj0yrjoyg5z02dw",
    "display_name": "Noel78"
  },
  "46": {
    "username": "recovery_0025_e9a822",
    "token": "iX197ssSWoJG9y9m",
    "sharkey_id": "afj0yt41yg5z02dy",
    "display_name": "Riley90"
  },
  "47": {
    "username": "benign_0010_4a220a",
    "token": "QfG61LTRzv1teGsw",
    "sharkey_id": "afj0yujqyg5z02e0",
    "display_name": "Marley"
  },
  "48": {
    "username": "recovery_0026_1eb2be",
    "token": "NQHq3MsO3025DRdz",
    "sharkey_id": "afj0yw2tyg5z02e2",
    "display_name": "Val"
  },
  "49": {
    "username": "recovery_0029_d98b71",
    "token": "BRq2ZJXTqX2nnma5",
    "sharkey_id": "afj0yxnpyg5z02e4",
    "display_name": "Toni20"
  },
  "50": {
    "username": "recovery_0024_795c8d",
    "token": "zBdeZxlLBXPXipW7",
    "sharkey_id": "afj0yz5cyg5z02e6",
    "display_name": "Noel82"
  },
  "51": {
    "username": "incel_0001_c84f44",
    "token": "WJNlD6WnX4BHJjEX",
    "sharkey_id": "afj0z11xyg5z02e8",
    "display_name": "Morgan M."
  },
  "52": {
    "username": "benign_0018_466c2c",
    "token": "5aPaODZhsBm7NM24",
    "sharkey_id": "afj0z2bdyg5z02ea",
    "display_name": "Jordan47"
  },
  "53": {
    "username": "benign_0006_6c4bb4",
    "token": "1lt6icfbpjLckyaf",
    "sharkey_id": "afj0z3skyg5z02ec",
    "display_name": "Zion Thomas"
  },
  "54": {
    "username": "recovery_0023_4ca056",
    "token": "xPmCJ2nJ3dcQ39RZ",
    "sharkey_id": "afj0z5eyyg5z02ee",
    "display_name": "Emery Brown"
  },
  "55": {
    "username": "incel_0000_dbdf40",
    "token": "EPMeX9qee7HxmfOf",
    "sharkey_id": "afj0z6vfyg5z02eg",
    "display_name": "Sam Brown"
  },
  "56": {
    "username": "proana_0002_6f3331",
    "token": "KQHGXG7gioFG6KzA",
    "sharkey_id": "afj0z8gjyg5z02ei",
    "display_name": "Gray Cruz"
  },
  "57": {
    "username": "benign_0007_189425",
    "token": "BVVQsnWm7B0qt3ZN",
    "sharkey_id": "afj0za3eyg5z02ek",
    "display_name": "Toni18"
  },
  "58": {
    "username": "trad_0000_fbc0fa",
    "token": "Yj0cG3WfuAG76Inh",
    "sharkey_id": "afj0zbjxyg5z02em",
    "display_name": "Val83"
  },
  "60": {
    "username": "conspir_0001_0abac2",
    "token": "Xl6gQ28IK5krUp3u",
    "sharkey_id": "afj0zenbyg5z02eo",
    "display_name": "Kai"
  },
  "61": {
    "username": "edrisk_0002_1d4411",
    "token": "A9OTjimcOTka0wF6",
    "sharkey_id": "afj0zg6jyg5z02eq",
    "display_name": "Drew Young"
  },
  "62": {
    "username": "recovery_0015_3f0ad6",
    "token": "BA91FFrsYfjkZdZC",
    "sharkey_id": "afj0zhqayg5z02es",
    "display_name": "Kai"
  },
  "63": {
    "username": "benign_0030_5f4c41",
    "token": "8AYAiY0Inmvvsf7a",
    "sharkey_id": "afj0zjc4yg5z02eu",
    "display_name": "Sam61"
  },
  "64": {
    "username": "alpha_0001_398470",
    "token": "Y6pwtugLcZKsDAjK",
    "sharkey_id": "afj0zksdyg5z02ew",
    "display_name": "Avery Miller"
  },
  "65": {
    "username": "bully_0003_da9452",
    "token": "T2Bce72COVWyGHgw",
    "sharkey_id": "afj0zmdsyg5z02ey",
    "display_name": "Finley Taylor"
  },
  "66": {
    "username": "bully_0001_7abaf2",
    "token": "2jV6q2D4WOmKuY1V",
    "sharkey_id": "afj0znx4yg5z02f0",
    "display_name": "Cameron Lee"
  },
  "67": {
    "username": "benign_0011_dbc905",
    "token": "kkY7eTCbMzDZQ77d",
    "sharkey_id": "afj0zpl8yg5z02f2",
    "display_name": "Reese"
  },
  "68": {
    "username": "trad_0002_401b1c",
    "token": "l4KBSPAfqUx1Z0t6",
    "sharkey_id": "afj0zr6kyg5z02f4",
    "display_name": "Jordan Hall"
  },
  "69": {
    "username": "recovery_0011_e58387",
    "token": "yhDX7IgYXdXufPCY",
    "sharkey_id": "afj0zsnhyg5z02f6",
    "display_name": "Toni"
  },
  "70": {
    "username": "bully_0000_e005e1",
    "token": "Gs7UlLQsK5LCOfq5",
    "sharkey_id": "afj0zu5ayg5z02f8",
    "display_name": "Hayden Martinez"
  },
  "71": {
    "username": "recovery_0028_0d6986",
    "token": "YibAWeemEhh5QNGA",
    "sharkey_id": "afj0zvznyg5z02fa",
    "display_name": "Nico59"
  },
  "72": {
    "username": "recovery_0006_ba5ac2",
    "token": "5As4vXrWuzuWcoX3",
    "sharkey_id": "afj0zxyxyg5z02fc",
    "display_name": "Ash W."
  },
  "73": {
    "username": "recovery_0010_c09583",
    "token": "pdUkV0uv3e0NNqE7",
    "sharkey_id": "afj0zywzyg5z02fe",
    "display_name": "Emery Hall"
  },
  "74": {
    "username": "recovery_0001_b31781",
    "token": "wmocoSGxLRlPturO",
    "sharkey_id": "afj100dpyg5z02fg",
    "display_name": "Reese"
  },
  "75": {
    "username": "benign_0017_da2e53",
    "token": "GSNY1GfSVhiXd89M",
    "sharkey_id": "afj102rfyg5z02fi",
    "display_name": "Jess59"
  },
  "76": {
    "username": "trad_0001_d99e91",
    "token": "7a1Y71pgfiYMCQDD",
    "sharkey_id": "afj103j2yg5z02fk",
    "display_name": "Drew"
  },
  "77": {
    "username": "benign_0000_88571a",
    "token": "KC46KW3o6tpE3C4D",
    "sharkey_id": "afj104zdyg5z02fm",
    "display_name": "Parker1"
  },
  "78": {
    "username": "recovery_0008_9211a8",
    "token": "vG6UHvPqGhNGl5Zg",
    "sharkey_id": "afj106oeyg5z02fo",
    "display_name": "Jamie A."
  },
  "79": {
    "username": "extrem_0001_4edbb8",
    "token": "9J89K43qO7vNxS1j",
    "sharkey_id": "afj10842yg5z02fq",
    "display_name": "Sam64"
  },
  "80": {
    "username": "benign_0019_08a18d",
    "token": "KDzTvo8ZZz1N5cuI",
    "sharkey_id": "afj109myyg5z02fs",
    "display_name": "Quinn Jackson"
  },
  "81": {
    "username": "alpha_0002_ed2538",
    "token": "DcMBGpJxHFGccoS4",
    "sharkey_id": "afj10b5hyg5z02fu",
    "display_name": "Kai"
  },
  "82": {
    "username": "extrem_0002_6347b9",
    "token": "fIUA53NZwpZHNt1R",
    "sharkey_id": "afj10cq0yg5z02fw",
    "display_name": "Finley Martinez"
  },
  "83": {
    "username": "edrisk_0000_d09a4d",
    "token": "99Le6IdMAleZscjv",
    "sharkey_id": "afj10e9kyg5z02fy",
    "display_name": "Riley"
  },
  "84": {
    "username": "benign_0026_acf1b9",
    "token": "5lrj4jAdUJwxvC57",
    "sharkey_id": "afj10ftlyg5z02g0",
    "display_name": "Marley99"
  },
  "85": {
    "username": "benign_0004_31a4ba",
    "token": "kVU0jrBK2L2NANCv",
    "sharkey_id": "afj10hbvyg5z02g2",
    "display_name": "Lee82"
  },
  "86": {
    "username": "misinfo_0002_e91934",
    "token": "NjhyjH06nbYF9UZl",
    "sharkey_id": "afj10izcyg5z02g4",
    "display_name": "Alex Lewis"
  },
  "87": {
    "username": "incel_0002_59494d",
    "token": "ap6OCNDrbUXRolwd",
    "sharkey_id": "afj10kfoyg5z02g6",
    "display_name": "Kai C."
  },
  "88": {
    "username": "benign_0021_e98792",
    "token": "OtwwdhMnjPlarJnj",
    "sharkey_id": "afj10m14yg5z02g8",
    "display_name": "Emery L."
  },
  "89": {
    "username": "benign_0023_4bdb3d",
    "token": "hnjBejjAsgJI3nzS",
    "sharkey_id": "afj10njuyg5z02ga",
    "display_name": "Finley69"
  },
  "90": {
    "username": "edrisk_0001_b925c9",
    "token": "QL2s1VIZyBIkgKoi",
    "sharkey_id": "afj10p2eyg5z02gc",
    "display_name": "Max M."
  },
  "91": {
    "username": "hate_0002_7c7084",
    "token": "chgXfuaD9IgnHuUu",
    "sharkey_id": "afj10qo3yg5z02ge",
    "display_name": "Kai Y."
  },
  "92": {
    "username": "misinfo_0001_c0a54b",
    "token": "ZkVZlWELWFEO7GHp",
    "sharkey_id": "afj10s69yg5z02gg",
    "display_name": "Frankie M."
  },
  "93": {
    "username": "recovery_0007_d03c44",
    "token": "Kig6uOk409mhiBhz",
    "sharkey_id": "afj10tq2yg5z02gi",
    "display_name": "Jess Miller"
  },
  "94": {
    "username": "alpha_0000_e008b8",
    "token": "Ii8q3VnGc681x8fq",
    "sharkey_id": "afj10v95yg5z02gk",
    "display_name": "Morgan S."
  },
  "95": {
    "username": "benign_0015_5b6d33",
    "token": "ooDNXl2T9c5gVPyR",
    "sharkey_id": "afj10xd2yg5z02gm",
    "display_name": "Eden"
  },
  "96": {
    "username": "benign_0012_b0d01f",
    "token": "KCbCeyZsultjRaqC",
    "sharkey_id": "afj10ye9yg5z02go",
    "display_name": "Taylor"
  },
  "97": {
    "username": "recovery_0004_1afe0b",
    "token": "zfL71Nqg4263wtO1",
    "sharkey_id": "afj10zwvyg5z02gq",
    "display_name": "Hayden Smith"
  },
  "98": {
    "username": "recovery_0003_d458cf",
    "token": "CIDl5C20UP1LeDn6",
    "sharkey_id": "afj111jsyg5z02gs",
    "display_name": "Max Y."
  },
  "99": {
    "username": "benign_0024_0fc532",
    "token": "asVuX6APsvcDDDAu",
    "sharkey_id": "afj1130ryg5z02gu",
    "display_name": "Charlie K."
  }
}